masstable/__init__.py
masstable/masstable.py
masstable/data/AME1995.txt
masstable/data/AME1995all.txt
masstable/data/AME2003.txt
masstable/data/AME2003all.txt
masstable/data/AME2012.txt
masstable/data/AME2012all.txt
masstable/data/BR2013.txt
masstable/data/DUZU.txt
masstable/data/ETFSI12.txt
masstable/data/FRDM95.txt
masstable/data/GK88.txt
masstable/data/HFB14.txt
masstable/data/HFB26.txt
masstable/data/KTUY05.txt
masstable/data/MAJA88.txt
masstable/data/SVM13.txt
masstable/data/TCSM12.txt
masstable/data/TCSM13.txt
masstable/data/WS32010.txt
masstable/data/WS32011.txt
masstable-0.4.1.dist-info/LICENSE
masstable-0.4.1.dist-info/WHEEL
masstable-0.4.1.dist-info/METADATA
masstable-0.4.1.dist-info/RECORD
