Metadata-Version: 2.1
Name: masstable
Version: 0.4.1
Summary: Utilities for working with nuclear mass tables
Home-page: https://github.com/elyase/masstable
Author: Yaser Martinez Palenzuela
Author-email: yaser.martinez@gmail.com
Requires-Python: >=3.7
Classifier: Programming Language :: Python :: 3.7
Classifier: Programming Language :: Python :: 3.8
Classifier: Programming Language :: Python :: 3 :: Only
Requires-Dist: pandas>=1.2.3
Project-URL: Documentation, https://elyase.github.io/masstable/
